{
    "@class": "Animation",
    "id": {
        "uuid": "1D9E0846-917D-497A-9246-B4C7D863D331"
    },
    "tracks": [
        {
            "@class": "BoolBehaviorTrack",
            "clips": [
                {
                    "@class": "BoolBehaviorClip",
                    "beginTime": 0,
                    "duration": 600,
                    "script": "BoolValueBehaviorClipScript",
                    "behavior": {
                        "@class": "BoolDiscreteBehavior",
                        "frames": [
                            {
                                "@class": "BoolKeyFrame",
                                "formula": {
                                    "@class": "BoolExpressionFormula",
                                    "expression": "false"
                                },
                                "time": 600
                            }
                        ]
                    }
                }
            ],
            "script": "BoolBehaviorTrackScript",
            "accessor": "Object3DEnabledBlendAccessor"
        }
    ]
}