{"@class":"Animation","id":{"uuid":"AF395C00-EA23-4E5A-90BD-EEDBA7478DCF"},"tracks":[{"@class":"FloatBehaviorTrack","clips":[{"@class":"FloatBehaviorClip","beginTime":0,"duration":0,"script":"FloatValueBehaviorClipScript","behavior":{"@class":"FloatBezierBehavior","frames":[{"@class":"FloatBezierKeyFrame","formula":{"@class":"FloatExpressionFormula","expression":"object__422BEFCD_CC79_4B70_8E8C_A0F0D83F91AD__Direction*-1"},"time":0,"point1":{"values":[0.0,0.0]},"point2":{"values":[0.0,0.0]},"order":"linear","transition":true}]}}],"script":"FloatBehaviorTrackScript","accessor":"FloatVariableAccessor","attribute":"Direction"}]}