{"@class":"Animation","id":{"uuid":"E2A5BDC1-86E4-4F5D-B9D0-B977372841BF"},"tracks":[{"@class":"SoundTrack","clips":[{"@class":"SoundClip","beginTime":3500,"duration":485,"script":"SoundClipScript","behavior":{"@class":"SoundSampleBehavior","volume":1.0,"volumeModulation":0.0,"pitch":1.0,"pitchModulation":0.0,"soundSampleId":{"uuid":"2204BB70-1748-45E1-B4E6-8EE07B878894"}},"color":{"values":[0.7411764860153198,0.21960784494876862,0.8117647171020508]}}],"script":"SoundTrackScript","accessor":"AudioSourceAccessor","volume":0.6833333373069763}]}