[
    {
        "@class": "BaseNode",
        "object3D": {
            "@class": "BaseObject3D",
            "id": {
                "uuid": "82B3F3A6-E689-4D5C-92AC-EB8995115D38"
            },
            "name": "Gioll_Attack",
            "enabled": true,
            "visible": true,
            "hitVisible": true,
            "timeline": {
                "@class": "BaseComponentTimeline",
                "timelineId": {
                    "uuid": "4816F2BE-B9F2-4803-A478-BF684EF8AE4B"
                }
            },
            "transform": {
                "@class": "BaseComponentTransformable",
                "localTransforms": {
                    "values": [
                        1.0,
                        0.0,
                        0.0,
                        0.0,
                        0.0,
                        1.0,
                        0.0,
                        0.0,
                        0.0,
                        0.0,
                        1.0,
                        0.0,
                        0.0,
                        0.0,
                        0.0,
                        1.0
                    ]
                },
                "globalTransforms": {
                    "values": [
                        1.0,
                        0.0,
                        0.0,
                        0.0,
                        0.0,
                        1.0,
                        0.0,
                        0.0,
                        0.0,
                        0.0,
                        1.0,
                        0.0,
                        89.8228530883789,
                        3.683257579803467,
                        0.0,
                        1.0
                    ]
                }
            },
            "metadata": {
                "importedIdentifier": "",
                "importedName": "",
                "isBone": false
            }
        },
        "asset_id": {
            "uuid": "C8D2C7B7-B775-4B01-86F9-2DF022631243"
        },
        "is_asset_root": false
    }
]