[
    {
        "@class": "BaseNode",
        "object3D": {
            "@class": "BaseObject3D",
            "id": {
                "uuid": "E221EB49-8C59-4C39-AC44-A4240955DE66"
            },
            "name": "Wall_part3 2",
            "enabled": true,
            "visible": true,
            "hitVisible": true,
            "geometry": {
                "@class": "BaseComponentGeometry",
                "meshId": {
                    "uuid": "1C4DF588-D2D7-4AFA-8634-2230C2A8A8EE"
                },
                "static": true,
                "shadowCast": true,
                "shadowReceive": true
            },
            "material": {
                "@class": "BaseComponentMaterial",
                "materialId": {
                    "uuid": "72DFFEBA-E39E-4B0E-9596-E6675E188CA8"
                },
                "mapsStates": 127
            },
            "transform": {
                "@class": "BaseComponentTransformable",
                "localTransforms": {
                    "values": [
                        1.0,
                        0.0,
                        0.0,
                        0.0,
                        0.0,
                        1.0,
                        0.0,
                        0.0,
                        0.0,
                        0.0,
                        1.0,
                        0.0,
                        5.399999618530273,
                        3.4999990463256838,
                        4.799998760223389,
                        1.0
                    ]
                },
                "globalTransforms": {
                    "values": [
                        1.0,
                        0.0,
                        0.0,
                        0.0,
                        0.0,
                        1.0,
                        0.0,
                        0.0,
                        0.0,
                        0.0,
                        1.0,
                        0.0,
                        98.5,
                        8.19999885559082,
                        2.5999979972839357,
                        1.0
                    ]
                }
            },
            "metadata": {
                "importedIdentifier": "defaultobject",
                "importedName": "defaultobject",
                "isBone": false
            }
        },
        "asset_id": {
            "uuid": "93DFDFBB-B3E5-4217-91C3-33D77C83F18D"
        },
        "is_asset_root": true,
        "asset_name": "Wall_part3"
    }
]