{"@class":"TimeLineScript","id":{"uuid":"31CAF1A0-E228-4066-8CA5-15014DE8D2DC"},"name":"Animation","enableOnAwake":false,"loop":true,"jumpToFirstFrameAtEnd":false,"speed":1.0,"weight":1.0,"loopStartTime":0,"loopDuration":0,"is_imported":false,"type":"user","scripts":{"@class":"StdListRuntimeScript","list":[{"@class":"AnimationScript","id":{"uuid":"2C206D1C-5039-4584-A149-9EA89243B836"},"name":"Speaker","enableOnAwake":false,"OwnerLink":{"@class":"BindingLink","targetId":{"uuid":"43D4B9DF-BDD7-4429-808B-0B3923E814A9"},"targetRelativeAddress":{"@class":"NodeRelativeAddressBase","index":4,"name":"River","subaddress":{"@class":"NodeRelativeAddressBase","index":4,"name":"Speaker"}}},"animation":{"uuid":"D6D19575-76BA-4BAD-80D7-36B23C84DC9F"},"AnimationType":"object3D","is_imported":false,"isEnabled":true}]},"triggers":[{"@class":"StartTrigger","id":{"uuid":"475A1602-70CC-4FB2-B993-F79122A69FEF"},"ownerScriptId":{"uuid":"31CAF1A0-E228-4066-8CA5-15014DE8D2DC"},"logicOperation":0,"resultType":0,"isInverted":false}]}