{"@class":"TimeLineScript","id":{"uuid":"44E2D78B-012B-42B0-B8F4-53DB9C5D33A4"},"name":"Animation","enableOnAwake":false,"loop":false,"jumpToFirstFrameAtEnd":false,"speed":1.0,"weight":1.0,"loopStartTime":0,"loopDuration":0,"is_imported":false,"type":"user","scripts":{"@class":"StdListRuntimeScript","list":[{"@class":"AnimationScript","id":{"uuid":"A1D9AE3F-87D0-4643-B822-101AE18CA81E"},"name":"Coin1","enableOnAwake":false,"OwnerLink":{"@class":"BindingLink","targetId":{"uuid":"034E29D4-D2F7-4B95-A479-E32E3FDB3733"},"targetRelativeAddress":{"@class":"NodeRelativeAddressBase","index":3,"name":"Coin 3","subaddress":{"@class":"NodeRelativeAddressBase","index":2,"name":"Coin1"}}},"animation":{"uuid":"5387CA64-7D4A-4C6F-B2A9-D63719DD167A"},"AnimationType":"object3D","is_imported":false,"isEnabled":true},{"@class":"AnimationScript","id":{"uuid":"0E007AFE-6448-4897-9704-2AD33B4A6741"},"name":"Coin2","enableOnAwake":false,"OwnerLink":{"@class":"BindingLink","targetId":{"uuid":"F270C723-9231-4585-BB3D-9930ED54544C"},"targetRelativeAddress":{"@class":"NodeRelativeAddressBase","index":3,"name":"Coin 3","subaddress":{"@class":"NodeRelativeAddressBase","index":3,"name":"Coin2"}}},"animation":{"uuid":"E0490C1D-7DB5-4CC3-A435-567AA8AC733F"},"AnimationType":"object3D","is_imported":false,"isEnabled":true},{"@class":"AnimationScript","id":{"uuid":"9F587F33-400A-4286-90ED-521984C96085"},"name":"Coin3","enableOnAwake":false,"OwnerLink":{"@class":"BindingLink","targetId":{"uuid":"2D32643D-69B5-48E7-B439-041E2A0EEA84"},"targetRelativeAddress":{"@class":"NodeRelativeAddressBase","index":3,"name":"Coin 3","subaddress":{"@class":"NodeRelativeAddressBase","index":1,"name":"Coin3"}}},"animation":{"uuid":"38D1ADD4-BC7F-4A8C-8101-DDFBCA2A68EB"},"AnimationType":"object3D","is_imported":false,"isEnabled":true},{"@class":"AnimationScript","id":{"uuid":"E11C74D8-7D17-43D7-9936-E7578984D19B"},"name":"Coin4","enableOnAwake":false,"OwnerLink":{"@class":"BindingLink","targetId":{"uuid":"1E34496A-7176-441B-87CD-B5BED449C9BB"},"targetRelativeAddress":{"@class":"NodeRelativeAddressBase","index":3,"name":"Coin 3","subaddress":{"@class":"NodeRelativeAddressBase","index":4,"name":"Coin4"}}},"animation":{"uuid":"07C3F8A5-9798-4183-B731-9788A4A593CF"},"AnimationType":"object3D","is_imported":false,"isEnabled":true},{"@class":"AnimationScript","id":{"uuid":"2F487961-1A50-4701-AAF9-12A69585C3A6"},"name":"Collider","enableOnAwake":false,"OwnerLink":{"@class":"BindingLink","targetId":{"uuid":"844F603F-71DC-4DC1-9F13-8D3A4491DA6E"},"targetRelativeAddress":{"@class":"NodeRelativeAddressBase","index":3,"name":"Coin 3","subaddress":{"@class":"NodeRelativeAddressBase","index":0,"name":"Collider"}}},"animation":{"uuid":"876BCC98-A145-4ABF-91F6-D883AD73F3E6"},"AnimationType":"object3D","is_imported":false,"isEnabled":true},{"@class":"AnimationScript","id":{"uuid":"6234057E-DEB8-47AE-BA5F-A6659B4E5F61"},"name":"Coin","enableOnAwake":false,"OwnerLink":{"@class":"BindingLink","targetId":{"uuid":"1558C433-66B5-4E8B-9B2D-265233630389"},"targetRelativeAddress":{"@class":"NodeRelativeAddressBase","index":3,"name":"Coin 3"}},"animation":{"uuid":"8207317E-F73A-4BFE-9ADF-E5C13B4AA85C"},"AnimationType":"object3D","is_imported":false,"isEnabled":true}]},"triggers":[{"@class":"AnimationTrigger","id":{"uuid":"C7A97646-E4F7-43D3-8641-BAE6D4D9E96E"},"ownerScriptId":{"uuid":"44E2D78B-012B-42B0-B8F4-53DB9C5D33A4"},"logicOperation":0,"resultType":0,"isInverted":false,"event":1,"bindingLink":{"@class":"BindingLink","targetId":{"uuid":"06BFCCF5-D657-4683-8B6D-200D3CCD2D21"}}},{"@class":"AnimationTrigger","id":{"uuid":"1944FAE1-E12B-4430-9D2C-2677563876F2"},"ownerScriptId":{"uuid":"44E2D78B-012B-42B0-B8F4-53DB9C5D33A4"},"logicOperation":0,"resultType":0,"isInverted":false,"event":1,"bindingLink":{"@class":"BindingLink","targetId":{"uuid":"202BBF2A-F9B8-45A3-BC69-5949AF178D67"}}}]}