{"@class":"TimeLineScript","id":{"uuid":"7272F7A4-57C2-4240-AF51-DA2BC33ACA04"},"name":"Animation","enableOnAwake":false,"loop":true,"jumpToFirstFrameAtEnd":false,"speed":1.0,"weight":1.0,"loopStartTime":0,"loopDuration":0,"is_imported":false,"type":"user","scripts":{"@class":"StdListRuntimeScript","list":[{"@class":"AnimationScript","id":{"uuid":"93D989D3-6BD3-4C53-A875-0014E0514169"},"name":"Guill_mesh","enableOnAwake":false,"OwnerLink":{"@class":"BindingLink","targetId":{"uuid":"0652483C-43CC-40AC-8248-F46CDDE42E94"},"targetRelativeAddress":{"@class":"NodeRelativeAddressBase","index":6,"name":"Guillotina 6","subaddress":{"@class":"NodeRelativeAddressBase","index":1,"name":"Guill_mesh"}}},"animation":{"uuid":"AAC4F613-293A-4307-B851-9DB77B995A22"},"AnimationType":"object3D","is_imported":false,"isEnabled":true},{"@class":"AnimationScript","id":{"uuid":"553C9EAA-FDC7-44FC-9035-E0E07718EE60"},"name":"Collider_Blade","enableOnAwake":false,"OwnerLink":{"@class":"BindingLink","targetId":{"uuid":"2A3AF6AB-B316-471F-AA46-188F74CB0E42"},"targetRelativeAddress":{"@class":"NodeRelativeAddressBase","index":6,"name":"Guillotina 6","subaddress":{"@class":"NodeRelativeAddressBase","index":0,"name":"Collider_Blade"}}},"animation":{"uuid":"AE1102FA-5E89-4386-B88D-A5776D1F80E7"},"AnimationType":"object3D","is_imported":false,"isEnabled":true}]},"triggers":[{"@class":"CollisionTrigger","id":{"uuid":"D4816C76-08C5-49C5-B1C4-4E57A8D4E518"},"ownerScriptId":{"uuid":"7272F7A4-57C2-4240-AF51-DA2BC33ACA04"},"logicOperation":0,"resultType":0,"isInverted":false,"eventType":"in","targetBindingLink":{"@class":"BindingLink","targetId":{"uuid":"2A3AF6AB-B316-471F-AA46-188F74CB0E42"}},"zoneBindingLink":{"@class":"BindingLink","targetId":{"uuid":"31EBB1D0-0156-4E6E-9077-8600F9FC9F62"}},"allowed":false}]}