{"@class":"TimeLineScript","id":{"uuid":"D60DCA6E-A6DE-4CA4-B193-72E1546C6A50"},"name":"Animation","enableOnAwake":false,"loop":false,"jumpToFirstFrameAtEnd":false,"speed":1.0,"weight":1.0,"loopStartTime":0,"loopDuration":0,"is_imported":false,"type":"user","scripts":{"@class":"StdListRuntimeScript","list":[{"@class":"AnimationScript","id":{"uuid":"8709735B-4155-4251-B6EE-D4B2A30254CC"},"name":"Coin1","enableOnAwake":false,"OwnerLink":{"@class":"BindingLink","targetId":{"uuid":"D753CAD3-DAFB-4D73-BB5D-44ABFF6B7A7E"},"targetRelativeAddress":{"@class":"NodeRelativeAddressBase","index":2,"name":"Coin 8","subaddress":{"@class":"NodeRelativeAddressBase","index":2,"name":"Coin1"}}},"animation":{"uuid":"E44CDC94-42E0-4F28-93C2-D0F5F17748A0"},"AnimationType":"object3D","is_imported":false,"isEnabled":true},{"@class":"AnimationScript","id":{"uuid":"D8036BA8-DF97-4D60-AD17-45043FD94F84"},"name":"Coin2","enableOnAwake":false,"OwnerLink":{"@class":"BindingLink","targetId":{"uuid":"9CD196F2-BC8E-4318-8800-6D29420A0503"},"targetRelativeAddress":{"@class":"NodeRelativeAddressBase","index":2,"name":"Coin 8","subaddress":{"@class":"NodeRelativeAddressBase","index":3,"name":"Coin2"}}},"animation":{"uuid":"D9C65CDB-0D10-4AE6-8AAE-D021EB062736"},"AnimationType":"object3D","is_imported":false,"isEnabled":true},{"@class":"AnimationScript","id":{"uuid":"27DA1A75-DE05-452A-B2EA-96AE69CD0F91"},"name":"Coin3","enableOnAwake":false,"OwnerLink":{"@class":"BindingLink","targetId":{"uuid":"ABF8A8F4-20E9-4FDB-894D-7B8CB461331C"},"targetRelativeAddress":{"@class":"NodeRelativeAddressBase","index":2,"name":"Coin 8","subaddress":{"@class":"NodeRelativeAddressBase","index":1,"name":"Coin3"}}},"animation":{"uuid":"C66BDAD3-B7B3-42A1-9CDC-C63904886465"},"AnimationType":"object3D","is_imported":false,"isEnabled":true},{"@class":"AnimationScript","id":{"uuid":"21C0A8CB-0ED5-4C2B-9418-850AA28B6923"},"name":"Coin4","enableOnAwake":false,"OwnerLink":{"@class":"BindingLink","targetId":{"uuid":"09E0513D-3A7B-4D62-93F3-70F13E793832"},"targetRelativeAddress":{"@class":"NodeRelativeAddressBase","index":2,"name":"Coin 8","subaddress":{"@class":"NodeRelativeAddressBase","index":4,"name":"Coin4"}}},"animation":{"uuid":"CC6E7DED-50C3-4CC5-84D7-1D7E9879DCBE"},"AnimationType":"object3D","is_imported":false,"isEnabled":true},{"@class":"AnimationScript","id":{"uuid":"37E33B55-76EC-42C3-8DDF-BD4AAB3C93F1"},"name":"Collider","enableOnAwake":false,"OwnerLink":{"@class":"BindingLink","targetId":{"uuid":"6107A83C-DC99-4526-8B94-F2F629E18CD3"},"targetRelativeAddress":{"@class":"NodeRelativeAddressBase","index":2,"name":"Coin 8","subaddress":{"@class":"NodeRelativeAddressBase","index":0,"name":"Collider"}}},"animation":{"uuid":"5ACA5492-0659-4FD9-8234-0B6F905028A0"},"AnimationType":"object3D","is_imported":false,"isEnabled":true},{"@class":"AnimationScript","id":{"uuid":"BEDA7932-07FB-4BBD-9966-EC8685F149EB"},"name":"Coin","enableOnAwake":false,"OwnerLink":{"@class":"BindingLink","targetId":{"uuid":"03B05428-A3A2-42BD-BF75-C3B33B3D6A02"},"targetRelativeAddress":{"@class":"NodeRelativeAddressBase","index":2,"name":"Coin 8"}},"animation":{"uuid":"1E56213C-66B4-44AE-8FB7-F5325DF0F1C1"},"AnimationType":"object3D","is_imported":false,"isEnabled":true},{"@class":"AnimationScript","id":{"uuid":"345F616E-A416-426E-B19D-7E04C5CBABF6"},"name":"Master Sound","enableOnAwake":false,"OwnerLink":{"@class":"BindingLink"},"animation":{"uuid":"C3BD9A63-CB9B-47A9-87DE-B15013F17AF3"},"AnimationType":"masterSound","is_imported":false,"isEnabled":true}]},"triggers":[{"@class":"CollisionTrigger","id":{"uuid":"F187CAFA-1088-4500-BD71-09754585BA7F"},"ownerScriptId":{"uuid":"D60DCA6E-A6DE-4CA4-B193-72E1546C6A50"},"logicOperation":0,"resultType":0,"isInverted":false,"eventType":"in","targetBindingLink":{"@class":"BindingLink","targetId":{"uuid":"2ECB3BA4-F2F4-42DD-86E8-322283040C6C"}},"zoneBindingLink":{"@class":"BindingLink","targetId":{"uuid":"6107A83C-DC99-4526-8B94-F2F629E18CD3"}},"allowed":false}]}